[
  {
    "first_name": "Andre",
    "last_name": "Green",
    "title":"Mr",
    "country_code": "1",
    "phone_number":"5555555550",
    "email":"andre@lattis.com",
    "username": "andre@lattis.io",
    "password": "andre",
    "date_created": 1473630768839,
    "user_state": "active"
  },
  {
    "first_name": "Jeremy",
    "last_name": "Ricard",
    "country_code": "1",
    "phone_number":"5555555551",
    "email":"jeremy@lattis.io",
    "username": "jeremy@lattis.io",
    "password": "jeremy",
    "date_created": 1472630767839,
    "user_state": "active"
  },
  {
    "first_name": "Jack",
    "last_name": "Al-Kahwati",
    "country_code": "1",
    "phone_number":"5555555552",
    "email":"jack@lattis.io",
    "username": "jack@lattis.io",
    "password": "jack",
    "date_created": 1472630760839,
    "user_state": "active"
  },
  {
    "first_name": "Jennifer",
    "last_name": "Payne",
    "country_code": "1",
    "phone_number":"5555555553",
    "email":"jennifer.payne@lattis.io",
    "username": "jennifer.payne@lattis.io",
    "password": "jennifer",
    "date_created": 1472630761839,
    "user_state": "active"
  },
  {
    "first_name": "Lauren",
    "last_name": "Wang",
    "country_code": "1",
    "phone_number":"5555555554",
    "email":"lauren@lattis.io",
    "username": "lauren@lattis.io",
    "password": "lauren",
    "date_created": 1472630768439,
    "user_state": "active"
  },
  {
    "first_name": "Shiva",
    "last_name": "Aratal",
    "country_code": "1",
    "phone_number":"5555555555",
    "email":"shiva@lattis.io",
    "username": "shiva@lattis.io",
    "password": "shiva",
    "date_created": 1472630758439,
    "user_state": "active"
  }
]
